langgraph_reducer/__init__.py
langgraph_reducer/reducer.py
langgraph_reducer-0.0.2.dist-info/METADATA
langgraph_reducer-0.0.2.dist-info/WHEEL
langgraph_reducer-0.0.2.dist-info/RECORD
